moval/__init__.py
moval/registry.py
moval/integrations/__init__.py
moval/integrations/sklearn/__init__.py
moval/integrations/sklearn/moval.py
moval/models/__init__.py
moval/models/confidences.py
moval/models/model.py
moval/models/solver_temperature.py
moval/models/utils.py
moval/solvers/__init__.py
moval/solvers/criterions.py
moval/solvers/solver.py
moval/solvers/utils.py
moval-0.3.25.dist-info/METADATA
moval-0.3.25.dist-info/WHEEL
moval-0.3.25.dist-info/top_level.txt
moval-0.3.25.dist-info/RECORD
