Metadata-Version: 2.1
Name: moval
Version: 0.3.25
Summary: Model evaluation without manual labels
Home-page: https://github.com/ZerojumpLine/MOVAL
Author: Zeju Li
Author-email: lizeju8@gmail.com
Project-URL: Bug Tracker, https://github.com/ZerojumpLine/MOVAL/issues
Classifier: Development Status :: 3 - Alpha
Classifier: Environment :: GPU :: NVIDIA CUDA
Classifier: Intended Audience :: Science/Research
Classifier: Operating System :: OS Independent
Classifier: Programming Language :: Python :: 3
Classifier: Topic :: Scientific/Engineering :: Artificial Intelligence
Classifier: License :: Free for non-commercial use
Requires-Python: >=3.8
Requires-Dist: scikit-learn >=1.3.0
Requires-Dist: scipy >=1.8.0
Requires-Dist: pytest
Requires-Dist: gdown
Requires-Dist: pandas
Requires-Dist: nibabel
